biasx/__init__.py
biasx/analyzer.py
biasx/calculators.py
biasx/config.py
biasx/datasets.py
biasx/explainers.py
biasx/models.py
biasx/types.py
biasx/utils.py
biasx/data/dataset_config.json
biasx/data/landmark_mapping.json
biasx/data/landmarker_config.json
biasx-0.1.3.dist-info/licenses/LICENSE
biasx-0.1.3.dist-info/METADATA
biasx-0.1.3.dist-info/WHEEL
biasx-0.1.3.dist-info/top_level.txt
biasx-0.1.3.dist-info/RECORD
