Metadata-Version: 2.4
Name: biasx
Version: 0.1.3
Summary: A toolkit for detecting and explaining gender bias in face classification models
Author-email: Rixdon Niño Mape <rixdonninorecario.mape@bicol-u.edu.ph>, Jerwin Glen Lucero <jerwinglenalejandre.lucero@bicol-u.edu.ph>, Jan Wilhelm Sy <janwilhelmtan.sy@bicol-u.edu.ph>
License: MIT License
Project-URL: Homepage, https://github.com/rixmape/biasx
Project-URL: Bug Tracker, https://github.com/rixmape/biasx/issues
Project-URL: Documentation, https://github.com/rixmape/biasx/blob/main/README.md
Classifier: Programming Language :: Python :: 3
Classifier: Programming Language :: Python :: 3.11
Classifier: License :: OSI Approved :: MIT License
Classifier: Operating System :: OS Independent
Classifier: Topic :: Scientific/Engineering :: Artificial Intelligence
Classifier: Topic :: Software Development :: Libraries :: Python Modules
Requires-Python: >=3.11
License-File: LICENSE
Requires-Dist: huggingface_hub
Requires-Dist: mediapipe
Requires-Dist: numpy
Requires-Dist: pandas
Requires-Dist: pillow
Requires-Dist: plotly
Requires-Dist: pyarrow
Requires-Dist: scikit-image
Requires-Dist: scikit-learn
Requires-Dist: scipy
Requires-Dist: tensorflow
Requires-Dist: tf_keras_vis
Dynamic: license-file
